wakdbe/__init__.py
wakdbe/__main__.py
wakdbe/protect.py
wakdbe/restore_whatsapp.py
wakdbe/view_extract.py
wakdbe/bin/7za.dll
wakdbe/bin/7za.exe
wakdbe/bin/7zxa.dll
wakdbe/bin/AdbWinApi.dll
wakdbe/bin/AdbWinUsbApi.dll
wakdbe/bin/SDL2.dll
wakdbe/bin/abe.jar
wakdbe/bin/adb.exe
wakdbe/bin/avcodec-58.dll
wakdbe/bin/avformat-58.dll
wakdbe/bin/avutil-56.dll
wakdbe/bin/curl.exe
wakdbe/bin/grep.exe
wakdbe/bin/libiconv2.dll
wakdbe/bin/libintl3.dll
wakdbe/bin/linux_dependencies.sh
wakdbe/bin/pcre3.dll
wakdbe/bin/regex2.dll
wakdbe/bin/scrcpy-console.bat
wakdbe/bin/scrcpy-noconsole.vbs
wakdbe/bin/scrcpy-server
wakdbe/bin/scrcpy.exe
wakdbe/bin/swresample-3.dll
wakdbe/bin/swscale-5.dll
wakdbe/bin/tar.exe
wakdbe/extracted/.placeholder
wakdbe/helpers/ADBDeviceSerialId.py
wakdbe/helpers/CustomCI.py
wakdbe/helpers/LinuxUSB.py
wakdbe/helpers/TCPDeviceSerialId.py
wakdbe/helpers/WIndowsUSB.py
wakdbe/helpers/__init__.py
wakdbe/non_essentials/todo.txt
wakdbe-0.4.1.dist-info/LICENSE
wakdbe-0.4.1.dist-info/METADATA
wakdbe-0.4.1.dist-info/WHEEL
wakdbe-0.4.1.dist-info/top_level.txt
wakdbe-0.4.1.dist-info/RECORD
