Metadata-Version: 2.1
Name: wakdbe
Version: 0.4.1
Summary: Extract WhatsApp key/DB from package directory (/data/data/com.whatsapp) without root access.
Home-page: https://github.com/yuvrajraghuvanshis/WhatsApp-Key-Database-Extractor
Author: Yuvraj Raghuvanshi
Author-email: YuvrajRaghuvanshi.S@protonmail.com
License: UNKNOWN
Project-URL: Bug Tracker, https://github.com/yuvrajraghuvanshis/WhatsApp-Key-Database-Extractor/issues
Platform: UNKNOWN
Classifier: Programming Language :: Python :: 3
Classifier: License :: OSI Approved :: MIT License
Classifier: Operating System :: OS Independent
Requires-Python: >=3.6
